README.rst
setup.py
Memcached_cli.egg-info/PKG-INFO
Memcached_cli.egg-info/SOURCES.txt
Memcached_cli.egg-info/dependency_links.txt
Memcached_cli.egg-info/entry_points.txt
Memcached_cli.egg-info/requires.txt
Memcached_cli.egg-info/top_level.txt
memcached_cli/__init__.py
memcached_cli/main.py