Metadata-Version: 1.1
Name: Memcached-cli
Version: 0.1.dev0
Summary: A client cli for Memcached Server,which write by python.
Home-page: https://bitbucket.org/yafeile/memcached-cli
Author: fly
Author-email: yafeile@sohu.com
License: BSD License
Keywords: memcached cli
Platform: Posix
Platform: Mac OS
Platform: Windows
Classifier: License :: OSI Approved :: BSD License
Classifier: Topic :: Database
Classifier: Programming Language :: Python
